pyvfx_boilerplate/__init__.py
pyvfx_boilerplate/boilerplate_ui.py
pyvfx_boilerplate/cli.py
pyvfx_boilerplate/init.py
pyvfx_boilerplate/mayapalette.py
pyvfx_boilerplate/menu.py
pyvfx_boilerplate/resources/main_window.ui
pyvfx_boilerplate/resources/module.ui
pyvfx_boilerplate/resources/qpalette_maya2015.json
pyvfx_boilerplate/resources/qpalette_maya2016.json
pyvfx_boilerplate/utils/__init__.py
pyvfx_boilerplate/utils/get_set_palette_data_qt4.py
pyvfx_boilerplate/utils/get_set_palette_data_qt5.py
pyvfx_boilerplate-3.2.4.dist-info/LICENSE
pyvfx_boilerplate-3.2.4.dist-info/METADATA
pyvfx_boilerplate-3.2.4.dist-info/WHEEL
pyvfx_boilerplate-3.2.4.dist-info/entry_points.txt
pyvfx_boilerplate-3.2.4.dist-info/top_level.txt
pyvfx_boilerplate-3.2.4.dist-info/RECORD
