Metadata-Version: 2.1
Name: pyvfx-boilerplate
Version: 3.2.4
Summary: A boilerplate Qt Py* app that runs in dcc apps, py2, or py3.
Home-page: https://github.com/fredrikaverpil/pyvfx-boilerplate
License: UNKNOWN
Platform: UNKNOWN
Classifier: Programming Language :: Python :: 2.7
Classifier: Programming Language :: Python :: 3.7
Classifier: License :: OSI Approved :: MIT License
Classifier: Operating System :: OS Independent
License-File: LICENSE
Requires-Dist: Qt.py
